schema/__init__.py
schema/myfunctions.py
cross_model_information-0.0.1.dist-info/LICENSE.txt
cross_model_information-0.0.1.dist-info/METADATA
cross_model_information-0.0.1.dist-info/WHEEL
cross_model_information-0.0.1.dist-info/top_level.txt
cross_model_information-0.0.1.dist-info/RECORD
